graphchem/__init__.py
graphchem/version.py
graphchem/data/__init__.py
graphchem/data/structs.py
graphchem/datasets/__init__.py
graphchem/datasets/sets.py
graphchem/datasets/static/cn.csv
graphchem/datasets/static/lhv.csv
graphchem/datasets/static/mon.csv
graphchem/datasets/static/ron.csv
graphchem/datasets/static/ysi.csv
graphchem/nn/__init__.py
graphchem/nn/gcn.py
graphchem/preprocessing/__init__.py
graphchem/preprocessing/features.py
graphchem-2.3.2.dist-info/LICENSE
graphchem-2.3.2.dist-info/METADATA
graphchem-2.3.2.dist-info/WHEEL
graphchem-2.3.2.dist-info/top_level.txt
graphchem-2.3.2.dist-info/RECORD
