Metadata-Version: 2.2
Name: graphchem
Version: 2.3.2
Summary: Graph-based machine learning for chemical property prediction
Author-email: Travis Kessler <travis.j.kessler@gmail.com>
Project-URL: Homepage, https://github.com/ecrl/graphchem
Project-URL: Bug Tracker, https://github.com/ecrl/graphchem/issues
Classifier: Programming Language :: Python :: 3.11
Classifier: License :: OSI Approved :: MIT License
Classifier: Operating System :: OS Independent
Requires-Python: >=3.11
License-File: LICENSE
Requires-Dist: rdkit-pypi==2022.9.5
Requires-Dist: torch==2.5.1
Requires-Dist: torch-geometric==2.6.1
